{
  "mode": "pre",
  "tag": "next",
  "initialVersions": {
    "@10up/headless-core": "0.4.4",
    "@10up/react-hooks": "1.2.3",
    "@10up/headless-next": "0.4.3",
    "@10up/headless-docs": "1.0.0",
    "@10up/wp-multisite-i18n-nextjs": "0.2.0",
    "@10up/wp-multisite-nextjs": "0.2.0",
    "@10up/wp-nextjs": "0.2.0"
  },
  "changesets": [
    "big-beers-try",
    "fluffy-mice-mate",
    "gold-cows-arrive",
    "lazy-seals-end",
    "lovely-rules-collect",
    "orange-pumpkins-notice",
    "quick-years-design",
    "smart-plants-explain"
  ]
}
